formset/__init__.py
formset/__main__.py
formset/formset.py
formset/py.typed
formtools_formset-1.0.0.dist-info/entry_points.txt
formtools_formset-1.0.0.dist-info/LICENSE
formtools_formset-1.0.0.dist-info/WHEEL
formtools_formset-1.0.0.dist-info/METADATA
formtools_formset-1.0.0.dist-info/RECORD
