Metadata-Version: 2.1
Name: formtools-formset
Version: 1.0.0
Summary: A form.set generator.
Home-page: https://github.com/tueda/formset
License: MIT
Keywords: configuration,form
Author: Takahiro Ueda
Author-email: tueda@st.seikei.ac.jp
Requires-Python: >=2.7, !=3.0.*, !=3.1.*
Classifier: Development Status :: 5 - Production/Stable
Classifier: Environment :: Console
Classifier: Intended Audience :: Science/Research
Classifier: License :: OSI Approved :: MIT License
Classifier: Programming Language :: Python :: 2
Classifier: Programming Language :: Python :: 2.7
Classifier: Programming Language :: Python :: 3
Classifier: Programming Language :: Python :: 3.4
Classifier: Programming Language :: Python :: 3.5
Classifier: Programming Language :: Python :: 3.6
Classifier: Programming Language :: Python :: 3.7
Classifier: Programming Language :: Python :: 3.8
Classifier: Programming Language :: Python :: 3.9
Classifier: Topic :: Scientific/Engineering :: Mathematics
Classifier: Topic :: Scientific/Engineering :: Physics
Classifier: Topic :: Utilities
Requires-Dist: argparse (>=1.4.0,<2.0.0); python_version >= "2.6" and python_version < "2.7"
Project-URL: Repository, https://github.com/tueda/formset
